nerveclient/__init__.py
nerveclient/client.py
nerveclient-0.1.3.dist-info/METADATA
nerveclient-0.1.3.dist-info/WHEEL
nerveclient-0.1.3.dist-info/top_level.txt
nerveclient-0.1.3.dist-info/RECORD
