Metadata-Version: 2.1
Name: nerveclient
Version: 0.1.3
Summary: A simple python client to send requests to the Nerve Engine.
Author-email: Matthew Prast <mprast@get-nerve.com>
Project-URL: Homepage, https://github.com/get-nerve/nerve-engine-clients
Project-URL: Issues, https://github.com/get-nerve/nerve-engine-clients/issues
Classifier: Programming Language :: Python :: 2
Classifier: Programming Language :: Python :: 3
Classifier: License :: OSI Approved :: MIT License
Classifier: Operating System :: OS Independent
Requires-Python: >=2.7
Requires-Dist: requests
